simple_clip/__init__.py
simple_clip/clip.py
simple_clip/imagenet_eval.py
simple_clip/utils.py
simple_clip/custom_datasets/__init__.py
simple_clip/custom_datasets/clip_datasets.py
simple_clip/encoders/__init__.py
simple_clip/encoders/image_encoders.py
simple_clip/encoders/text_encoders.py
simple_clip-0.2.0.data/scripts/run_training.py
simple_clip-0.2.0.data/scripts/train.py
simple_clip-0.2.0.dist-info/LICENSE
simple_clip-0.2.0.dist-info/METADATA
simple_clip-0.2.0.dist-info/WHEEL
simple_clip-0.2.0.dist-info/entry_points.txt
simple_clip-0.2.0.dist-info/top_level.txt
simple_clip-0.2.0.dist-info/RECORD
