Metadata-Version: 2.1
Name: simple-clip
Version: 0.2.0
Summary: A minimal, but effective implementation of CLIP (Contrastive Language-Image Pretraining) in PyTorch
Home-page: https://github.com/filipbasara0/simple-clip
Author: Filip Basara
Author-email: basarafilip@gmail.com
License: MIT
Keywords: machine learning,pytorch,self-supervised learning,representation learning,contrastive learning
Platform: UNKNOWN
Classifier: Development Status :: 4 - Beta
Classifier: Intended Audience :: Developers
Classifier: Topic :: Scientific/Engineering :: Artificial Intelligence
Classifier: License :: OSI Approved :: MIT License
Classifier: Programming Language :: Python :: 3.10
Requires-Dist: datasets (>=2.15)
Requires-Dist: scikit-learn (>=1.3.2)
Requires-Dist: torch (>=2.1)
Requires-Dist: torchinfo (>=1.8.0)
Requires-Dist: torchvision (>=0.16)
Requires-Dist: tqdm (>=4.66)
Requires-Dist: transformers (>=4.35)
Requires-Dist: webdataset (>=0.2.77)
